myoons_ocr/__init__.py
myoons_ocr/google_ocr.py
myoons_ocr-0.1.dist-info/METADATA
myoons_ocr-0.1.dist-info/WHEEL
myoons_ocr-0.1.dist-info/top_level.txt
myoons_ocr-0.1.dist-info/RECORD
